Metadata-Version: 1.2
Name: teModels
Version: 0.9
Summary: Example Models for Tellurium
Home-page: http://tellurium.analogmachine.org
Author: H M Sauro
Author-email: hsauro@uw.edu
License: MIT
Platform: UNKNOWN
Classifier: License :: OSI Approved :: MIT License
Classifier: Programming Language :: Python :: 3.6
Classifier: Programming Language :: Python :: 3.7
Classifier: Operating System :: OS Independent
Requires-Python: >=3.6
